pytseg/__init__.py
pytseg/__version__.py
pytseg/data.py
pytseg/plot.py
pytseg/seg.py
pytseg/seg_multi.py
pytseg-0.1.dist-info/LICENSE
pytseg-0.1.dist-info/METADATA
pytseg-0.1.dist-info/WHEEL
pytseg-0.1.dist-info/top_level.txt
pytseg-0.1.dist-info/RECORD
