Metadata-Version: 2.1
Name: pytseg
Version: 0.1
Summary: Tiny toolbox for time series segmentation
Home-page: https://github.com/RaoulHeese/pytseq
Download-URL: https://github.com/RaoulHeese/pytseq/releases
Author: Raoul Heese
Author-email: raoul.heese@gmail.com
Maintainer: Raoul Heese
Maintainer-email: raoul.heese@gmail.com
License: MIT
Project-URL: Bug Tracker, https://github.com/RaoulHeese/pytseq/issues
Project-URL: Source Code, https://github.com/RaoulHeese/pytseq
Classifier: License :: OSI Approved :: MIT License
Classifier: Intended Audience :: Science/Research
License-File: LICENSE
Requires-Dist: numpy
Requires-Dist: scipy
Requires-Dist: scikit-learn
Requires-Dist: matplotlib
Requires-Dist: typing
